{
    "wordInfoList": [
        {
            "word": "engagement",
            "clipfn": "May26-Sessions/engagement",
            "scale": 1.0,
            "pos": {
                "x": 1.264654278755188,
                "y": 1.5029876232147217,
                "z": 2.205662727355957
            },
            "rot": {
                "x": -0.03605471923947334,
                "y": 0.3481280207633972,
                "z": 0.01044661644846201,
                "w": 0.9366951584815979
            }
        },
        {
            "word": "ethereal",
            "clipfn": "May26-Sessions/ethereal",
            "scale": 1.0,
            "pos": {
                "x": 0.24711906909942628,
                "y": 1.9322750568389893,
                "z": 1.8211911916732789
            },
            "rot": {
                "x": 0.0970342680811882,
                "y": -0.23391132056713105,
                "z": -0.11834070831537247,
                "w": -0.960138201713562
            }
        },
        {
            "word": "hello",
            "clipfn": "May26-Sessions/hello",
            "scale": 1.0,
            "pos": {
                "x": -1.7448939085006714,
                "y": 1.705333948135376,
                "z": 1.1394456624984742
            },
            "rot": {
                "x": -0.1788615733385086,
                "y": -0.30589911341667178,
                "z": 0.2712657153606415,
                "w": 0.8949018120765686
            }
        },
        {
            "word": "illusory",
            "clipfn": "May26-Sessions/illusory",
            "scale": 1.0,
            "pos": {
                "x": -0.6023607850074768,
                "y": 2.419437885284424,
                "z": 1.351686954498291
            },
            "rot": {
                "x": 0.2955878674983978,
                "y": -0.03194013983011246,
                "z": -0.028777893632650377,
                "w": -0.9543476700782776
            }
        },
        {
            "word": "permanent",
            "clipfn": "May26-Sessions/permanent",
            "scale": 1.0,
            "pos": {
                "x": -0.8556865453720093,
                "y": 1.8119804859161378,
                "z": 1.5845117568969727
            },
            "rot": {
                "x": -0.10195823013782501,
                "y": -0.04714660719037056,
                "z": -0.0038766227662563326,
                "w": 0.9936632513999939
            }
        },
        {
            "word": "unrealized",
            "clipfn": "May26-Sessions/unrealized",
            "scale": 1.0,
            "pos": {
                "x": 0.8781283497810364,
                "y": 1.8020119667053223,
                "z": 1.001312255859375
            },
            "rot": {
                "x": -0.1934773176908493,
                "y": 0.39969658851623537,
                "z": -0.18559181690216065,
                "w": 0.8765642642974854
            }
        },
        {
            "word": "breathing",
            "clipfn": "May26-Sessions/breathing",
            "scale": 1.0,
            "pos": {
                "x": -1.405860424041748,
                "y": 1.2434377670288087,
                "z": 1.5144929885864258
            },
            "rot": {
                "x": 0.006262678653001785,
                "y": 0.19268597662448884,
                "z": -0.23378543555736543,
                "w": -0.9529833793640137
            }
        },
        {
            "word": "",
            "clipfn": "May26-Sessions/aaah",
            "scale": 1.0,
            "pos": {
                "x": -0.7756527662277222,
                "y": 1.184212565422058,
                "z": 1.3095324039459229
            },
            "rot": {
                "x": -0.09523440897464752,
                "y": 0.03229782357811928,
                "z": -0.13126060366630555,
                "w": -0.9862342476844788
            }
        },
        {
            "word": "",
            "clipfn": "May26-Sessions/omm",
            "scale": 1.0,
            "pos": {
                "x": -1.2470382452011109,
                "y": 2.114670753479004,
                "z": 1.0507489442825318
            },
            "rot": {
                "x": -0.27324625849723818,
                "y": -0.11305354535579682,
                "z": 0.2519305348396301,
                "w": 0.9214588403701782
            }
        },
        {
            "word": "",
            "clipfn": "May26-Sessions/omm2",
            "scale": 1.0,
            "pos": {
                "x": -0.2069227695465088,
                "y": 1.1184686422348023,
                "z": 1.4890607595443726
            },
            "rot": {
                "x": 0.11542414873838425,
                "y": 0.13038669526576997,
                "z": 0.1462753862142563,
                "w": 0.9737967848777771
            }
        },
        {
            "word": "",
            "clipfn": "May26-Sessions/chikichika",
            "scale": 1.0,
            "pos": {
                "x": -0.22693327069282533,
                "y": 1.5034438371658326,
                "z": 1.0038098096847535
            },
            "rot": {
                "x": -0.020733922719955446,
                "y": -0.21546779572963715,
                "z": -0.1618131399154663,
                "w": -0.9627877473831177
            }
        }
    ]
}